README.md
setup.py
ledger_event/__init__.py
ledger_event/constants.py
ledger_item/__init__.py
ledger_item/constants.py
ledger_payable/__init__.py
ledger_payable/constants.py
ledger_utils/__init__.py
ledger_utils/py_enum.py
mps_ledger_lib_wish.egg-info/PKG-INFO
mps_ledger_lib_wish.egg-info/SOURCES.txt
mps_ledger_lib_wish.egg-info/dependency_links.txt
mps_ledger_lib_wish.egg-info/top_level.txt
scripts/__init__.py